homely/__init__.py
homely/_asyncioutils.py
homely/_cli.py
homely/_engine2.py
homely/_errors.py
homely/_ui.py
homely/_utils.py
homely/files.py
homely/general.py
homely/install.py
homely/pipinstall.py
homely/powerline.py
homely/system.py
homely/ui.py
homely/_test/__init__.py
homely/_test/system.py
homely/_vcs/__init__.py
homely/_vcs/git.py
homely/_vcs/testhandler.py
homely-0.20.2.dist-info/METADATA
homely-0.20.2.dist-info/WHEEL
homely-0.20.2.dist-info/entry_points.txt
homely-0.20.2.dist-info/licenses/LICENSE
homely-0.20.2.dist-info/RECORD
